netbox_proxbox/__init__.py
netbox_proxbox/admin.py
netbox_proxbox/api/__init__.py
netbox_proxbox/api/serializers.py
netbox_proxbox/api/urls.py
netbox_proxbox/api/views.py
netbox_proxbox/example.py
netbox_proxbox/fastapi/main.py
netbox_proxbox/filters.py
netbox_proxbox/forms.py
netbox_proxbox/github.py
netbox_proxbox/icon_classes.py
netbox_proxbox/main.py
netbox_proxbox/migrations/0001_initial.py
netbox_proxbox/migrations/0002_vmresources_description.py
netbox_proxbox/migrations/0003_auto_20210419_2330.py
netbox_proxbox/migrations/__init__.py
netbox_proxbox/models.py
netbox_proxbox/navigation.py
netbox_proxbox/proxbox_api/README.md
netbox_proxbox/proxbox_api/__init__.py
netbox_proxbox/proxbox_api/create/__init__.py
netbox_proxbox/proxbox_api/create/dcim.py
netbox_proxbox/proxbox_api/create/extras.py
netbox_proxbox/proxbox_api/create/virtualization.py
netbox_proxbox/proxbox_api/deploy_fastapi.py
netbox_proxbox/proxbox_api/main.py
netbox_proxbox/proxbox_api/main_old.py
netbox_proxbox/proxbox_api/plugins_config.py
netbox_proxbox/proxbox_api/remove.py
netbox_proxbox/proxbox_api/update.py
netbox_proxbox/proxbox_api/updates/__init__.py
netbox_proxbox/proxbox_api/updates/extras.py
netbox_proxbox/proxbox_api/updates/node.py
netbox_proxbox/proxbox_api/updates/virtual_machine.py
netbox_proxbox/proxbox_api/virtual_machine.py
netbox_proxbox/release.py
netbox_proxbox/static/netbox_proxbox/discord-banner.png
netbox_proxbox/static/netbox_proxbox/discord.png
netbox_proxbox/static/netbox_proxbox/fastapi_logo.png
netbox_proxbox/static/netbox_proxbox/github.png
netbox_proxbox/static/netbox_proxbox/linkedin.png
netbox_proxbox/static/netbox_proxbox/proxmox-logo.svg
netbox_proxbox/static/netbox_proxbox/styles/_cable_trace.scss
netbox_proxbox/static/netbox_proxbox/styles/_dark.scss
netbox_proxbox/static/netbox_proxbox/styles/_external.scss
netbox_proxbox/static/netbox_proxbox/styles/_light.scss
netbox_proxbox/static/netbox_proxbox/styles/_print.scss
itjamie_netbox_proxbox-0.0.5.dist-info/LICENSE
itjamie_netbox_proxbox-0.0.5.dist-info/METADATA
itjamie_netbox_proxbox-0.0.5.dist-info/WHEEL
itjamie_netbox_proxbox-0.0.5.dist-info/RECORD
